Metadata-Version: 2.1
Name: ofacd
Version: 0.1.0
Summary: Organize files and clean directories
Home-page: https://pypi.org/project/ofacd
Download-URL: https://github.com/ames0k0/ofacd
Author: Nodaa Gaji
Author-email: c0d3r.nodiru.gaji@gmail.com
License: License :: OSI Approved :: MIT License
Platform: Operating System :: OS Independent
Classifier: Programming Language :: Python :: 3.10
License-File: LICENSE
